api_caller/__init__.py
api_caller/caller.py
lib/__init__.py
lib/caller.py
api_caller_pip_example-0.1.0.dist-info/METADATA
api_caller_pip_example-0.1.0.dist-info/WHEEL
api_caller_pip_example-0.1.0.dist-info/top_level.txt
api_caller_pip_example-0.1.0.dist-info/RECORD
