Metadata-Version: 2.1
Name: api-caller-pip-example
Version: 0.1.0
Summary: Simple Python library
Author: Me
License: MIT
Requires-Dist: requests
